class_registry/__init__.py
class_registry/auto_register.py
class_registry/base.py
class_registry/cache.py
class_registry/entry_points.py
class_registry/patcher.py
class_registry/py.typed
class_registry/registry.py
phx_class_registry-5.1.1.dist-info/LICENCE.txt
phx_class_registry-5.1.1.dist-info/METADATA
phx_class_registry-5.1.1.dist-info/WHEEL
phx_class_registry-5.1.1.dist-info/RECORD
