Metadata-Version: 2.1
Name: phx-class-registry
Version: 5.1.1
Summary: Factory+Registry pattern for Python classes
Home-page: https://github.com/todofixthis/class-registry
License: MIT
Keywords: design pattern,factory pattern,registry pattern,service registry
Author: Phoenix Zerin
Author-email: phx@phx.nz
Requires-Python: >=3.11,<4.0
Classifier: Development Status :: 5 - Production/Stable
Classifier: Intended Audience :: Developers
Classifier: License :: OSI Approved :: MIT License
Classifier: Programming Language :: Python :: 3
Classifier: Programming Language :: Python :: 3.11
Classifier: Programming Language :: Python :: 3.12
Classifier: Programming Language :: Python :: 3.13
Classifier: Topic :: Software Development :: Libraries :: Python Modules
Project-URL: Changelog, https://github.com/todofixthis/class-registry/releases
Project-URL: Documentation, https://class-registry.readthedocs.io/
Project-URL: Issues, https://github.com/todofixthis/class-registry/issues
Project-URL: Repository, https://github.com/todofixthis/class-registry
